setup.py
bin/fcon
fcon/__init__.py
fcon.egg-info/PKG-INFO
fcon.egg-info/SOURCES.txt
fcon.egg-info/dependency_links.txt
fcon.egg-info/requires.txt
fcon.egg-info/top_level.txt