Metadata-Version: 1.0
Name: fcon
Version: 1.1.0
Summary: show the files which contains the content you want to search.
Home-page: https://github.com/pmars/tools/tree/master/fcon
Author: xiaoh
Author-email: xiaoh@about.me
License: MIT Licence
Keywords: find,fcon,xiaoh,search,content
Platform: any
